[
  {
    "title": "Pokmon Anime_L4",
    "link_thumb": "https://live.staticflickr.com/65535/51787959580_4a6502080d_o.gif",
    "id_album": "-555824141",
    "total": 108,
    "size_max_detail_page": 3,
    "list_detail": [
      {
        "index_page": 0,
        "link_page": "https://github.com/lmbstudiocontact/mb4_dt_alb_0/raw/main/14132021_dta_-555824141_index_0.json"
      },
      {
        "index_page": 1,
        "link_page": "https://github.com/lmbstudiocontact/mb4_dt_alb_0/raw/main/14132021_dta_-555824141_index_1.json"
      },
      {
        "index_page": 2,
        "link_page": "https://github.com/lmbstudiocontact/mb4_dt_alb_0/raw/main/14132021_dta_-555824141_index_2.json"
      }
    ]
  },
  {
    "title": "Simpsons Cartoon_L7",
    "link_thumb": "https://live.staticflickr.com/65535/51786326707_51104f7e40_o.gif",
    "id_album": "1276946594",
    "total": 8,
    "size_max_detail_page": 1,
    "list_detail": [
      {
        "index_page": 0,
        "link_page": "https://github.com/lmbstudiocontact/mb4_dt_alb_0/raw/main/14132021_dta_1276946594_index_0.json"
      }
    ]
  },
  {
    "title": "Angry Birds_L10",
    "link_thumb": "https://live.staticflickr.com/65535/51787144793_07f8e1a114_o.gif",
    "id_album": "1070098567",
    "total": 26,
    "size_max_detail_page": 1,
    "list_detail": [
      {
        "index_page": 0,
        "link_page": "https://github.com/lmbstudiocontact/mb4_dt_alb_0/raw/main/14132021_dta_1070098567_index_0.json"
      }
    ]
  },
  {
    "title": "Ragnarok_L5",
    "link_thumb": "https://live.staticflickr.com/65535/51787737594_086e3cccd4_o.gif",
    "id_album": "1601322213",
    "total": 15,
    "size_max_detail_page": 1,
    "list_detail": [
      {
        "index_page": 0,
        "link_page": "https://github.com/lmbstudiocontact/mb4_dt_alb_0/raw/main/14132021_dta_1601322213_index_0.json"
      }
    ]
  },
  {
    "title": "Kitty & My Melody_L7",
    "link_thumb": "https://live.staticflickr.com/65535/51787279543_b5c07f3134_o.gif",
    "id_album": "-378480539",
    "total": 76,
    "size_max_detail_page": 2,
    "list_detail": [
      {
        "index_page": 0,
        "link_page": "https://github.com/lmbstudiocontact/mb4_dt_alb_0/raw/main/14132021_dta_-378480539_index_0.json"
      },
      {
        "index_page": 1,
        "link_page": "https://github.com/lmbstudiocontact/mb4_dt_alb_0/raw/main/14132021_dta_-378480539_index_1.json"
      }
    ]
  },
  {
    "title": "Detective Conan_L3",
    "link_thumb": "https://live.staticflickr.com/65535/51786132787_7a75da31da_o.gif",
    "id_album": "-1285383390",
    "total": 14,
    "size_max_detail_page": 1,
    "list_detail": [
      {
        "index_page": 0,
        "link_page": "https://github.com/lmbstudiocontact/mb4_dt_alb_0/raw/main/14132021_dta_-1285383390_index_0.json"
      }
    ]
  },
  {
    "title": "Lilo & Stitch Cartoon_L3",
    "link_thumb": "https://live.staticflickr.com/65535/51787897840_95a957eb1f_o.gif",
    "id_album": "685543661",
    "total": 30,
    "size_max_detail_page": 1,
    "list_detail": [
      {
        "index_page": 0,
        "link_page": "https://github.com/lmbstudiocontact/mb4_dt_alb_0/raw/main/14132021_dta_685543661_index_0.json"
      }
    ]
  },
  {
    "title": "Spider Man Cartoon_L3",
    "link_thumb": "https://live.staticflickr.com/65535/51788000600_819577077d_o.gif",
    "id_album": "1735002393",
    "total": 16,
    "size_max_detail_page": 1,
    "list_detail": [
      {
        "index_page": 0,
        "link_page": "https://github.com/lmbstudiocontact/mb4_dt_alb_0/raw/main/14132021_dta_1735002393_index_0.json"
      }
    ]
  },
  {
    "title": "Angry Birds_L4",
    "link_thumb": "https://live.staticflickr.com/65535/51786917196_d880acbd1c_o.gif",
    "id_album": "2112729292",
    "total": 26,
    "size_max_detail_page": 1,
    "list_detail": [
      {
        "index_page": 0,
        "link_page": "https://github.com/lmbstudiocontact/mb4_dt_alb_0/raw/main/14132021_dta_2112729292_index_0.json"
      }
    ]
  },
  {
    "title": "Winnie the Pooh, A Winnie the Pooh Thanksgiving, The Many Adventures of Winnie the Pooh Cartoon",
    "link_thumb": "https://live.staticflickr.com/65535/51787525394_fa343e32f1_o.gif",
    "id_album": "-2045291929",
    "total": 2,
    "size_max_detail_page": 1,
    "list_detail": [
      {
        "index_page": 0,
        "link_page": "https://github.com/lmbstudiocontact/mb4_dt_alb_0/raw/main/14132021_dta_-2045291929_index_0.json"
      }
    ]
  },
  {
    "title": "Onmyoji_L3",
    "link_thumb": "https://live.staticflickr.com/65535/51787346098_f487e6735e_o.gif",
    "id_album": "389318915",
    "total": 26,
    "size_max_detail_page": 1,
    "list_detail": [
      {
        "index_page": 0,
        "link_page": "https://github.com/lmbstudiocontact/mb4_dt_alb_0/raw/main/14132021_dta_389318915_index_0.json"
      }
    ]
  },
  {
    "title": "Kitty & My Melody_L6",
    "link_thumb": "https://live.staticflickr.com/65535/51787895340_b0a6431e94_o.gif",
    "id_album": "-378480540",
    "total": 76,
    "size_max_detail_page": 2,
    "list_detail": [
      {
        "index_page": 0,
        "link_page": "https://github.com/lmbstudiocontact/mb4_dt_alb_0/raw/main/14132021_dta_-378480540_index_0.json"
      },
      {
        "index_page": 1,
        "link_page": "https://github.com/lmbstudiocontact/mb4_dt_alb_0/raw/main/14132021_dta_-378480540_index_1.json"
      }
    ]
  },
  {
    "title": "Naruto Anime_L6",
    "link_thumb": "https://live.staticflickr.com/65535/51786236402_9328445d37_o.gif",
    "id_album": "1894397988",
    "total": 37,
    "size_max_detail_page": 1,
    "list_detail": [
      {
        "index_page": 0,
        "link_page": "https://github.com/lmbstudiocontact/mb4_dt_alb_0/raw/main/14132021_dta_1894397988_index_0.json"
      }
    ]
  },
  {
    "title": "Onmyoji_L5",
    "link_thumb": "https://live.staticflickr.com/65535/51787959765_c81c873555_o.gif",
    "id_album": "389318917",
    "total": 26,
    "size_max_detail_page": 1,
    "list_detail": [
      {
        "index_page": 0,
        "link_page": "https://github.com/lmbstudiocontact/mb4_dt_alb_0/raw/main/14132021_dta_389318917_index_0.json"
      }
    ]
  },
  {
    "title": "Chibi",
    "link_thumb": "https://live.staticflickr.com/65535/51787761950_f50cefa462_o.gif",
    "id_album": "65078219",
    "total": 75,
    "size_max_detail_page": 2,
    "list_detail": [
      {
        "index_page": 0,
        "link_page": "https://github.com/lmbstudiocontact/mb4_dt_alb_0/raw/main/14132021_dta_65078219_index_0.json"
      },
      {
        "index_page": 1,
        "link_page": "https://github.com/lmbstudiocontact/mb4_dt_alb_0/raw/main/14132021_dta_65078219_index_1.json"
      }
    ]
  },
  {
    "title": "Music_L3",
    "link_thumb": "https://live.staticflickr.com/65535/51787648184_572488813f_o.gif",
    "id_album": "908522977",
    "total": 24,
    "size_max_detail_page": 1,
    "list_detail": [
      {
        "index_page": 0,
        "link_page": "https://github.com/lmbstudiocontact/mb4_dt_alb_0/raw/main/14132021_dta_908522977_index_0.json"
      }
    ]
  },
  {
    "title": "Pokmon Anime_L6",
    "link_thumb": "https://live.staticflickr.com/65535/51787987855_7944f1e8bc_o.gif",
    "id_album": "-555824139",
    "total": 108,
    "size_max_detail_page": 3,
    "list_detail": [
      {
        "index_page": 0,
        "link_page": "https://github.com/lmbstudiocontact/mb4_dt_alb_0/raw/main/14132021_dta_-555824139_index_0.json"
      },
      {
        "index_page": 1,
        "link_page": "https://github.com/lmbstudiocontact/mb4_dt_alb_0/raw/main/14132021_dta_-555824139_index_1.json"
      },
      {
        "index_page": 2,
        "link_page": "https://github.com/lmbstudiocontact/mb4_dt_alb_0/raw/main/14132021_dta_-555824139_index_2.json"
      }
    ]
  },
  {
    "title": "Cute Art_L7",
    "link_thumb": "https://live.staticflickr.com/65535/51786942131_bd3d88d1af_o.gif",
    "id_album": "-629963484",
    "total": 76,
    "size_max_detail_page": 2,
    "list_detail": [
      {
        "index_page": 0,
        "link_page": "https://github.com/lmbstudiocontact/mb4_dt_alb_0/raw/main/14132021_dta_-629963484_index_0.json"
      },
      {
        "index_page": 1,
        "link_page": "https://github.com/lmbstudiocontact/mb4_dt_alb_0/raw/main/14132021_dta_-629963484_index_1.json"
      }
    ]
  },
  {
    "title": "Butterfly_L1",
    "link_thumb": "https://live.staticflickr.com/65535/51787516534_01455c395b_o.gif",
    "id_album": "657564369",
    "total": 6,
    "size_max_detail_page": 1,
    "list_detail": [
      {
        "index_page": 0,
        "link_page": "https://github.com/lmbstudiocontact/mb4_dt_alb_0/raw/main/14132021_dta_657564369_index_0.json"
      }
    ]
  },
  {
    "title": "Fox Art_L6",
    "link_thumb": "https://live.staticflickr.com/65535/51787214443_354311e608_o.gif",
    "id_album": "-646110857",
    "total": 7,
    "size_max_detail_page": 1,
    "list_detail": [
      {
        "index_page": 0,
        "link_page": "https://github.com/lmbstudiocontact/mb4_dt_alb_0/raw/main/14132021_dta_-646110857_index_0.json"
      }
    ]
  },
  {
    "title": "Detective Conan_L1",
    "link_thumb": "https://live.staticflickr.com/65535/51787181788_62f0c63935_o.gif",
    "id_album": "-1285383392",
    "total": 16,
    "size_max_detail_page": 1,
    "list_detail": [
      {
        "index_page": 0,
        "link_page": "https://github.com/lmbstudiocontact/mb4_dt_alb_0/raw/main/14132021_dta_-1285383392_index_0.json"
      }
    ]
  },
  {
    "title": "Football_L9",
    "link_thumb": "https://live.staticflickr.com/65535/51787594904_d32bd03b6e_o.gif",
    "id_album": "-371026081",
    "total": 49,
    "size_max_detail_page": 1,
    "list_detail": [
      {
        "index_page": 0,
        "link_page": "https://github.com/lmbstudiocontact/mb4_dt_alb_0/raw/main/14132021_dta_-371026081_index_0.json"
      }
    ]
  },
  {
    "title": "Lilo & Stitch Cartoon_L7",
    "link_thumb": "https://live.staticflickr.com/65535/51787276098_b78a09a093_o.gif",
    "id_album": "685543665",
    "total": 30,
    "size_max_detail_page": 1,
    "list_detail": [
      {
        "index_page": 0,
        "link_page": "https://github.com/lmbstudiocontact/mb4_dt_alb_0/raw/main/14132021_dta_685543665_index_0.json"
      }
    ]
  },
  {
    "title": "Football_L1",
    "link_thumb": "https://live.staticflickr.com/65535/51787586594_7b72bf6343_o.gif",
    "id_album": "-371026089",
    "total": 49,
    "size_max_detail_page": 1,
    "list_detail": [
      {
        "index_page": 0,
        "link_page": "https://github.com/lmbstudiocontact/mb4_dt_alb_0/raw/main/14132021_dta_-371026089_index_0.json"
      }
    ]
  },
  {
    "title": "Buddhist Terms_L4",
    "link_thumb": "https://live.staticflickr.com/65535/51786096722_d7a47e244c_o.gif",
    "id_album": "518853931",
    "total": 13,
    "size_max_detail_page": 1,
    "list_detail": [
      {
        "index_page": 0,
        "link_page": "https://github.com/lmbstudiocontact/mb4_dt_alb_0/raw/main/14132021_dta_518853931_index_0.json"
      }
    ]
  },
  {
    "title": "Shiv_L4",
    "link_thumb": "https://live.staticflickr.com/65535/51787768254_51a66df05c_o.gif",
    "id_album": "-568595355",
    "total": 32,
    "size_max_detail_page": 1,
    "list_detail": [
      {
        "index_page": 0,
        "link_page": "https://github.com/lmbstudiocontact/mb4_dt_alb_0/raw/main/14132021_dta_-568595355_index_0.json"
      }
    ]
  },
  {
    "title": "Halloween Ghost Witch_L9",
    "link_thumb": "https://live.staticflickr.com/65535/51786171212_1ee7639e11_o.gif",
    "id_album": "1746571241",
    "total": 49,
    "size_max_detail_page": 1,
    "list_detail": [
      {
        "index_page": 0,
        "link_page": "https://github.com/lmbstudiocontact/mb4_dt_alb_0/raw/main/14132021_dta_1746571241_index_0.json"
      }
    ]
  },
  {
    "title": "Boku No Hero Academia Anime_L5",
    "link_thumb": "https://live.staticflickr.com/65535/51787544334_fc03cb49fd_o.gif",
    "id_album": "197312543",
    "total": 19,
    "size_max_detail_page": 1,
    "list_detail": [
      {
        "index_page": 0,
        "link_page": "https://github.com/lmbstudiocontact/mb4_dt_alb_0/raw/main/14132021_dta_197312543_index_0.json"
      }
    ]
  },
  {
    "title": "Donald Duck Cartoon_L4",
    "link_thumb": "https://live.staticflickr.com/65535/51787566799_e30e6e39fe_o.gif",
    "id_album": "-1917621482",
    "total": 4,
    "size_max_detail_page": 1,
    "list_detail": [
      {
        "index_page": 0,
        "link_page": "https://github.com/lmbstudiocontact/mb4_dt_alb_0/raw/main/14132021_dta_-1917621482_index_0.json"
      }
    ]
  },
  {
    "title": "Ratatouille Cartoon_L7",
    "link_thumb": "https://live.staticflickr.com/65535/51787121311_79c253e27d_o.gif",
    "id_album": "1746345506",
    "total": 5,
    "size_max_detail_page": 1,
    "list_detail": [
      {
        "index_page": 0,
        "link_page": "https://github.com/lmbstudiocontact/mb4_dt_alb_0/raw/main/14132021_dta_1746345506_index_0.json"
      }
    ]
  },
  {
    "title": "One Punch Man Anime_L4",
    "link_thumb": "https://live.staticflickr.com/65535/51787942215_a5db9cd955_o.gif",
    "id_album": "-1626855611",
    "total": 2,
    "size_max_detail_page": 1,
    "list_detail": [
      {
        "index_page": 0,
        "link_page": "https://github.com/lmbstudiocontact/mb4_dt_alb_0/raw/main/14132021_dta_-1626855611_index_0.json"
      }
    ]
  },
  {
    "title": "Buddhist Terms_L10",
    "link_thumb": "https://live.staticflickr.com/65535/51787159873_7d1659465b_o.gif",
    "id_album": "-1095397368",
    "total": 13,
    "size_max_detail_page": 1,
    "list_detail": [
      {
        "index_page": 0,
        "link_page": "https://github.com/lmbstudiocontact/mb4_dt_alb_0/raw/main/14132021_dta_-1095397368_index_0.json"
      }
    ]
  },
  {
    "title": "Boss Baby Cartoon_L3",
    "link_thumb": "https://live.staticflickr.com/65535/51786906126_d86ce3999b_o.gif",
    "id_album": "158762703",
    "total": 16,
    "size_max_detail_page": 1,
    "list_detail": [
      {
        "index_page": 0,
        "link_page": "https://github.com/lmbstudiocontact/mb4_dt_alb_0/raw/main/14132021_dta_158762703_index_0.json"
      }
    ]
  },
  {
    "title": "Halloween Ghost Witch_L2",
    "link_thumb": "https://live.staticflickr.com/65535/51786982126_a7f18c475c_o.gif",
    "id_album": "1746571234",
    "total": 49,
    "size_max_detail_page": 1,
    "list_detail": [
      {
        "index_page": 0,
        "link_page": "https://github.com/lmbstudiocontact/mb4_dt_alb_0/raw/main/14132021_dta_1746571234_index_0.json"
      }
    ]
  },
  {
    "title": "Donald Duck Cartoon_L6",
    "link_thumb": "https://live.staticflickr.com/65535/51787565944_76d8c33ac4_o.gif",
    "id_album": "-1917621480",
    "total": 4,
    "size_max_detail_page": 1,
    "list_detail": [
      {
        "index_page": 0,
        "link_page": "https://github.com/lmbstudiocontact/mb4_dt_alb_0/raw/main/14132021_dta_-1917621480_index_0.json"
      }
    ]
  },
  {
    "title": "Madagascar Cartoon_L7",
    "link_thumb": "https://live.staticflickr.com/65535/51787014941_01088bab4e_o.gif",
    "id_album": "-2014542384",
    "total": 9,
    "size_max_detail_page": 1,
    "list_detail": [
      {
        "index_page": 0,
        "link_page": "https://github.com/lmbstudiocontact/mb4_dt_alb_0/raw/main/14132021_dta_-2014542384_index_0.json"
      }
    ]
  },
  {
    "title": "Detective Conan_L5",
    "link_thumb": "https://live.staticflickr.com/65535/51787568534_95ae1c06a5_o.gif",
    "id_album": "-1285383388",
    "total": 16,
    "size_max_detail_page": 1,
    "list_detail": [
      {
        "index_page": 0,
        "link_page": "https://github.com/lmbstudiocontact/mb4_dt_alb_0/raw/main/14132021_dta_-1285383388_index_0.json"
      }
    ]
  },
  {
    "title": "Smurf Houses Cartoon_L3",
    "link_thumb": "https://live.staticflickr.com/65535/51787136646_923e896b2a_o.gif",
    "id_album": "228264852",
    "total": 4,
    "size_max_detail_page": 1,
    "list_detail": [
      {
        "index_page": 0,
        "link_page": "https://github.com/lmbstudiocontact/mb4_dt_alb_0/raw/main/14132021_dta_228264852_index_0.json"
      }
    ]
  },
  {
    "title": "Halloween Ghost Witch_L6",
    "link_thumb": "https://live.staticflickr.com/65535/51786988661_d45c1abe63_o.gif",
    "id_album": "1746571238",
    "total": 49,
    "size_max_detail_page": 1,
    "list_detail": [
      {
        "index_page": 0,
        "link_page": "https://github.com/lmbstudiocontact/mb4_dt_alb_0/raw/main/14132021_dta_1746571238_index_0.json"
      }
    ]
  },
  {
    "title": "Language Turkish",
    "link_thumb": "https://live.staticflickr.com/65535/51787145888_2901a48ca4_o.gif",
    "id_album": "-458571524",
    "total": 37,
    "size_max_detail_page": 1,
    "list_detail": [
      {
        "index_page": 0,
        "link_page": "https://github.com/lmbstudiocontact/mb4_dt_alb_0/raw/main/14132021_dta_-458571524_index_0.json"
      }
    ]
  },
  {
    "title": "Anime_Animation",
    "link_thumb": "https://live.staticflickr.com/65535/51786079352_f77ae0b345_o.gif",
    "id_album": "402419001",
    "total": 94,
    "size_max_detail_page": 2,
    "list_detail": [
      {
        "index_page": 0,
        "link_page": "https://github.com/lmbstudiocontact/mb4_dt_alb_0/raw/main/14132021_dta_402419001_index_0.json"
      },
      {
        "index_page": 1,
        "link_page": "https://github.com/lmbstudiocontact/mb4_dt_alb_0/raw/main/14132021_dta_402419001_index_1.json"
      }
    ]
  },
  {
    "title": "Naruto Anime_L10",
    "link_thumb": "https://live.staticflickr.com/65535/51787667149_149ab7ae77_o.gif",
    "id_album": "-1403204623",
    "total": 37,
    "size_max_detail_page": 1,
    "list_detail": [
      {
        "index_page": 0,
        "link_page": "https://github.com/lmbstudiocontact/mb4_dt_alb_0/raw/main/14132021_dta_-1403204623_index_0.json"
      }
    ]
  },
  {
    "title": "Butterfly_L3",
    "link_thumb": "https://live.staticflickr.com/65535/51787176258_2d553196e4_o.gif",
    "id_album": "657564371",
    "total": 6,
    "size_max_detail_page": 1,
    "list_detail": [
      {
        "index_page": 0,
        "link_page": "https://github.com/lmbstudiocontact/mb4_dt_alb_0/raw/main/14132021_dta_657564371_index_0.json"
      }
    ]
  },
  {
    "title": "Futurama Cartoon",
    "link_thumb": "https://live.staticflickr.com/65535/51786904831_6ffc39028c_o.gif",
    "id_album": "-1561576479",
    "total": 5,
    "size_max_detail_page": 1,
    "list_detail": [
      {
        "index_page": 0,
        "link_page": "https://github.com/lmbstudiocontact/mb4_dt_alb_0/raw/main/14132021_dta_-1561576479_index_0.json"
      }
    ]
  },
  {
    "title": "One Piece Anime_L2",
    "link_thumb": "https://live.staticflickr.com/65535/51787305788_4bb3ae8dc0_o.gif",
    "id_album": "1351456605",
    "total": 135,
    "size_max_detail_page": 3,
    "list_detail": [
      {
        "index_page": 0,
        "link_page": "https://github.com/lmbstudiocontact/mb4_dt_alb_0/raw/main/14132021_dta_1351456605_index_0.json"
      },
      {
        "index_page": 1,
        "link_page": "https://github.com/lmbstudiocontact/mb4_dt_alb_0/raw/main/14132021_dta_1351456605_index_1.json"
      },
      {
        "index_page": 2,
        "link_page": "https://github.com/lmbstudiocontact/mb4_dt_alb_0/raw/main/14132021_dta_1351456605_index_2.json"
      }
    ]
  },
  {
    "title": "Shiv_L2",
    "link_thumb": "https://live.staticflickr.com/65535/51788007965_c954567705_o.gif",
    "id_album": "-568595357",
    "total": 32,
    "size_max_detail_page": 1,
    "list_detail": [
      {
        "index_page": 0,
        "link_page": "https://github.com/lmbstudiocontact/mb4_dt_alb_0/raw/main/14132021_dta_-568595357_index_0.json"
      }
    ]
  },
  {
    "title": "Games",
    "link_thumb": "https://live.staticflickr.com/65535/51787146663_dda3580912_o.gif",
    "id_album": "68567713",
    "total": 321,
    "size_max_detail_page": 7,
    "list_detail": [
      {
        "index_page": 0,
        "link_page": "https://github.com/lmbstudiocontact/mb4_dt_alb_0/raw/main/14132021_dta_68567713_index_0.json"
      },
      {
        "index_page": 1,
        "link_page": "https://github.com/lmbstudiocontact/mb4_dt_alb_0/raw/main/14132021_dta_68567713_index_1.json"
      },
      {
        "index_page": 2,
        "link_page": "https://github.com/lmbstudiocontact/mb4_dt_alb_0/raw/main/14132021_dta_68567713_index_2.json"
      },
      {
        "index_page": 3,
        "link_page": "https://github.com/lmbstudiocontact/mb4_dt_alb_0/raw/main/14132021_dta_68567713_index_3.json"
      },
      {
        "index_page": 4,
        "link_page": "https://github.com/lmbstudiocontact/mb4_dt_alb_0/raw/main/14132021_dta_68567713_index_4.json"
      },
      {
        "index_page": 5,
        "link_page": "https://github.com/lmbstudiocontact/mb4_dt_alb_0/raw/main/14132021_dta_68567713_index_5.json"
      },
      {
        "index_page": 6,
        "link_page": "https://github.com/lmbstudiocontact/mb4_dt_alb_0/raw/main/14132021_dta_68567713_index_6.json"
      }
    ]
  },
  {
    "title": "One Punch Man Anime_L5",
    "link_thumb": "https://live.staticflickr.com/65535/51787069371_bd2aff738f_o.gif",
    "id_album": "-1626855610",
    "total": 2,
    "size_max_detail_page": 1,
    "list_detail": [
      {
        "index_page": 0,
        "link_page": "https://github.com/lmbstudiocontact/mb4_dt_alb_0/raw/main/14132021_dta_-1626855610_index_0.json"
      }
    ]
  },
  {
    "title": "Frozen Cartoon_L10",
    "link_thumb": "https://live.staticflickr.com/65535/51786137607_cf63f7ca57_o.gif",
    "id_album": "788725146",
    "total": 11,
    "size_max_detail_page": 1,
    "list_detail": [
      {
        "index_page": 0,
        "link_page": "https://github.com/lmbstudiocontact/mb4_dt_alb_0/raw/main/14132021_dta_788725146_index_0.json"
      }
    ]
  },
  {
    "title": "Horror Art_L7",
    "link_thumb": "https://live.staticflickr.com/65535/51787865935_2f8d658af6_o.gif",
    "id_album": "529377277",
    "total": 41,
    "size_max_detail_page": 1,
    "list_detail": [
      {
        "index_page": 0,
        "link_page": "https://github.com/lmbstudiocontact/mb4_dt_alb_0/raw/main/14132021_dta_529377277_index_0.json"
      }
    ]
  }
]