[
  {
    "title": "Donald Duck Cartoon_L4",
    "link_thumb": "https://live.staticflickr.com/65535/51787566799_e30e6e39fe_o.gif",
    "id_album": "-1917621482",
    "total": 4,
    "size_max_detail_page": 1,
    "list_detail": [
      {
        "index_page": 0,
        "link_page": "https://github.com/lmbstudiocontact/mb4_dt_alb_0/raw/main/14132021_dta_-1917621482_index_0.json"
      }
    ]
  },
  {
    "title": "Halloween Ghost Witch_L9",
    "link_thumb": "https://live.staticflickr.com/65535/51786171212_1ee7639e11_o.gif",
    "id_album": "1746571241",
    "total": 49,
    "size_max_detail_page": 1,
    "list_detail": [
      {
        "index_page": 0,
        "link_page": "https://github.com/lmbstudiocontact/mb4_dt_alb_0/raw/main/14132021_dta_1746571241_index_0.json"
      }
    ]
  },
  {
    "title": "Language Italian",
    "link_thumb": "https://live.staticflickr.com/65535/51787146023_0f542069e3_o.gif",
    "id_album": "-1675477192",
    "total": 37,
    "size_max_detail_page": 1,
    "list_detail": [
      {
        "index_page": 0,
        "link_page": "https://github.com/lmbstudiocontact/mb4_dt_alb_0/raw/main/14132021_dta_-1675477192_index_0.json"
      }
    ]
  },
  {
    "title": "Mickey Cartoon_L5",
    "link_thumb": "https://live.staticflickr.com/65535/51787644684_ec9745b499_o.gif",
    "id_album": "1680949826",
    "total": 22,
    "size_max_detail_page": 1,
    "list_detail": [
      {
        "index_page": 0,
        "link_page": "https://github.com/lmbstudiocontact/mb4_dt_alb_0/raw/main/14132021_dta_1680949826_index_0.json"
      }
    ]
  },
  {
    "title": "Madagascar Cartoon_L8",
    "link_thumb": "https://live.staticflickr.com/65535/51787636499_b4a6a62eef_o.gif",
    "id_album": "-2014542383",
    "total": 9,
    "size_max_detail_page": 1,
    "list_detail": [
      {
        "index_page": 0,
        "link_page": "https://github.com/lmbstudiocontact/mb4_dt_alb_0/raw/main/14132021_dta_-2014542383_index_0.json"
      }
    ]
  },
  {
    "title": "Kitty & My Melody_L7",
    "link_thumb": "https://live.staticflickr.com/65535/51787279543_b5c07f3134_o.gif",
    "id_album": "-378480539",
    "total": 76,
    "size_max_detail_page": 2,
    "list_detail": [
      {
        "index_page": 0,
        "link_page": "https://github.com/lmbstudiocontact/mb4_dt_alb_0/raw/main/14132021_dta_-378480539_index_0.json"
      },
      {
        "index_page": 1,
        "link_page": "https://github.com/lmbstudiocontact/mb4_dt_alb_0/raw/main/14132021_dta_-378480539_index_1.json"
      }
    ]
  },
  {
    "title": "Smurf Houses Cartoon_L3",
    "link_thumb": "https://live.staticflickr.com/65535/51787136646_923e896b2a_o.gif",
    "id_album": "228264852",
    "total": 4,
    "size_max_detail_page": 1,
    "list_detail": [
      {
        "index_page": 0,
        "link_page": "https://github.com/lmbstudiocontact/mb4_dt_alb_0/raw/main/14132021_dta_228264852_index_0.json"
      }
    ]
  },
  {
    "title": "Panda Art_L3",
    "link_thumb": "https://live.staticflickr.com/65535/51786269167_0c1a671101_o.gif",
    "id_album": "586574345",
    "total": 5,
    "size_max_detail_page": 1,
    "list_detail": [
      {
        "index_page": 0,
        "link_page": "https://github.com/lmbstudiocontact/mb4_dt_alb_0/raw/main/14132021_dta_586574345_index_0.json"
      }
    ]
  },
  {
    "title": "Joker Harley Quinn_L3",
    "link_thumb": "https://live.staticflickr.com/65535/51787864120_ea218244e5_o.gif",
    "id_album": "-2022175635",
    "total": 24,
    "size_max_detail_page": 1,
    "list_detail": [
      {
        "index_page": 0,
        "link_page": "https://github.com/lmbstudiocontact/mb4_dt_alb_0/raw/main/14132021_dta_-2022175635_index_0.json"
      }
    ]
  },
  {
    "title": "Couple_L2",
    "link_thumb": "https://live.staticflickr.com/65535/51786098522_53d5c490da_o.gif",
    "id_album": "-888889819",
    "total": 24,
    "size_max_detail_page": 1,
    "list_detail": [
      {
        "index_page": 0,
        "link_page": "https://github.com/lmbstudiocontact/mb4_dt_alb_0/raw/main/14132021_dta_-888889819_index_0.json"
      }
    ]
  },
  {
    "title": "Butterfly_L3",
    "link_thumb": "https://live.staticflickr.com/65535/51787176258_2d553196e4_o.gif",
    "id_album": "657564371",
    "total": 6,
    "size_max_detail_page": 1,
    "list_detail": [
      {
        "index_page": 0,
        "link_page": "https://github.com/lmbstudiocontact/mb4_dt_alb_0/raw/main/14132021_dta_657564371_index_0.json"
      }
    ]
  },
  {
    "title": "Animals",
    "link_thumb": "https://live.staticflickr.com/65535/51786080827_95f4473e73_o.gif",
    "id_album": "807717335",
    "total": 114,
    "size_max_detail_page": 3,
    "list_detail": [
      {
        "index_page": 0,
        "link_page": "https://github.com/lmbstudiocontact/mb4_dt_alb_0/raw/main/14132021_dta_807717335_index_0.json"
      },
      {
        "index_page": 1,
        "link_page": "https://github.com/lmbstudiocontact/mb4_dt_alb_0/raw/main/14132021_dta_807717335_index_1.json"
      },
      {
        "index_page": 2,
        "link_page": "https://github.com/lmbstudiocontact/mb4_dt_alb_0/raw/main/14132021_dta_807717335_index_2.json"
      }
    ]
  },
  {
    "title": "Couple_L7",
    "link_thumb": "https://live.staticflickr.com/65535/51786920606_fa5537aaba_o.gif",
    "id_album": "-888889814",
    "total": 24,
    "size_max_detail_page": 1,
    "list_detail": [
      {
        "index_page": 0,
        "link_page": "https://github.com/lmbstudiocontact/mb4_dt_alb_0/raw/main/14132021_dta_-888889814_index_0.json"
      }
    ]
  },
  {
    "title": "Animal Art_L2",
    "link_thumb": "https://live.staticflickr.com/65535/51787538139_10a052e355_o.gif",
    "id_album": "97007462",
    "total": 7,
    "size_max_detail_page": 1,
    "list_detail": [
      {
        "index_page": 0,
        "link_page": "https://github.com/lmbstudiocontact/mb4_dt_alb_0/raw/main/14132021_dta_97007462_index_0.json"
      }
    ]
  },
  {
    "title": "Naruto Anime_L9",
    "link_thumb": "https://live.staticflickr.com/65535/51787671969_99a9c6dfda_o.gif",
    "id_album": "1894397991",
    "total": 37,
    "size_max_detail_page": 1,
    "list_detail": [
      {
        "index_page": 0,
        "link_page": "https://github.com/lmbstudiocontact/mb4_dt_alb_0/raw/main/14132021_dta_1894397991_index_0.json"
      }
    ]
  },
  {
    "title": "Plants Vs Zombies_L9",
    "link_thumb": "https://live.staticflickr.com/65535/51787962470_cda488e083_o.gif",
    "id_album": "-1426777462",
    "total": 24,
    "size_max_detail_page": 1,
    "list_detail": [
      {
        "index_page": 0,
        "link_page": "https://github.com/lmbstudiocontact/mb4_dt_alb_0/raw/main/14132021_dta_-1426777462_index_0.json"
      }
    ]
  },
  {
    "title": "Couple_L4",
    "link_thumb": "https://live.staticflickr.com/65535/51787168243_1fe7ae16c0_o.gif",
    "id_album": "-888889817",
    "total": 24,
    "size_max_detail_page": 1,
    "list_detail": [
      {
        "index_page": 0,
        "link_page": "https://github.com/lmbstudiocontact/mb4_dt_alb_0/raw/main/14132021_dta_-888889817_index_0.json"
      }
    ]
  },
  {
    "title": "One Piece Anime_L6",
    "link_thumb": "https://live.staticflickr.com/65535/51787053351_1ce4ec8969_o.gif",
    "id_album": "1351456609",
    "total": 135,
    "size_max_detail_page": 3,
    "list_detail": [
      {
        "index_page": 0,
        "link_page": "https://github.com/lmbstudiocontact/mb4_dt_alb_0/raw/main/14132021_dta_1351456609_index_0.json"
      },
      {
        "index_page": 1,
        "link_page": "https://github.com/lmbstudiocontact/mb4_dt_alb_0/raw/main/14132021_dta_1351456609_index_1.json"
      },
      {
        "index_page": 2,
        "link_page": "https://github.com/lmbstudiocontact/mb4_dt_alb_0/raw/main/14132021_dta_1351456609_index_2.json"
      }
    ]
  },
  {
    "title": "Other 3",
    "link_thumb": "https://live.staticflickr.com/65535/51787156808_3d26c2273f_o.gif",
    "id_album": "518493955",
    "total": 533,
    "size_max_detail_page": 11,
    "list_detail": [
      {
        "index_page": 0,
        "link_page": "https://github.com/lmbstudiocontact/mb4_dt_alb_0/raw/main/14132021_dta_518493955_index_0.json"
      },
      {
        "index_page": 1,
        "link_page": "https://github.com/lmbstudiocontact/mb4_dt_alb_0/raw/main/14132021_dta_518493955_index_1.json"
      },
      {
        "index_page": 2,
        "link_page": "https://github.com/lmbstudiocontact/mb4_dt_alb_0/raw/main/14132021_dta_518493955_index_2.json"
      },
      {
        "index_page": 3,
        "link_page": "https://github.com/lmbstudiocontact/mb4_dt_alb_0/raw/main/14132021_dta_518493955_index_3.json"
      },
      {
        "index_page": 4,
        "link_page": "https://github.com/lmbstudiocontact/mb4_dt_alb_0/raw/main/14132021_dta_518493955_index_4.json"
      },
      {
        "index_page": 5,
        "link_page": "https://github.com/lmbstudiocontact/mb4_dt_alb_0/raw/main/14132021_dta_518493955_index_5.json"
      },
      {
        "index_page": 6,
        "link_page": "https://github.com/lmbstudiocontact/mb4_dt_alb_0/raw/main/14132021_dta_518493955_index_6.json"
      },
      {
        "index_page": 7,
        "link_page": "https://github.com/lmbstudiocontact/mb4_dt_alb_0/raw/main/14132021_dta_518493955_index_7.json"
      },
      {
        "index_page": 8,
        "link_page": "https://github.com/lmbstudiocontact/mb4_dt_alb_0/raw/main/14132021_dta_518493955_index_8.json"
      },
      {
        "index_page": 9,
        "link_page": "https://github.com/lmbstudiocontact/mb4_dt_alb_0/raw/main/14132021_dta_518493955_index_9.json"
      },
      {
        "index_page": 10,
        "link_page": "https://github.com/lmbstudiocontact/mb4_dt_alb_0/raw/main/14132021_dta_518493955_index_10.json"
      }
    ]
  },
  {
    "title": "The Peanuts Cartoon",
    "link_thumb": "https://live.staticflickr.com/65535/51787155373_240d2c8b0d_o.gif",
    "id_album": "342715601",
    "total": 6,
    "size_max_detail_page": 1,
    "list_detail": [
      {
        "index_page": 0,
        "link_page": "https://github.com/lmbstudiocontact/mb4_dt_alb_0/raw/main/14132021_dta_342715601_index_0.json"
      }
    ]
  },
  {
    "title": "Shiv_L7",
    "link_thumb": "https://live.staticflickr.com/65535/51787766874_76f6e5b2ec_o.gif",
    "id_album": "-568595352",
    "total": 32,
    "size_max_detail_page": 1,
    "list_detail": [
      {
        "index_page": 0,
        "link_page": "https://github.com/lmbstudiocontact/mb4_dt_alb_0/raw/main/14132021_dta_-568595352_index_0.json"
      }
    ]
  },
  {
    "title": "Pokmon Anime_L9",
    "link_thumb": "https://live.staticflickr.com/65535/51787119011_68ea8ca36b_o.gif",
    "id_album": "-555824136",
    "total": 108,
    "size_max_detail_page": 3,
    "list_detail": [
      {
        "index_page": 0,
        "link_page": "https://github.com/lmbstudiocontact/mb4_dt_alb_0/raw/main/14132021_dta_-555824136_index_0.json"
      },
      {
        "index_page": 1,
        "link_page": "https://github.com/lmbstudiocontact/mb4_dt_alb_0/raw/main/14132021_dta_-555824136_index_1.json"
      },
      {
        "index_page": 2,
        "link_page": "https://github.com/lmbstudiocontact/mb4_dt_alb_0/raw/main/14132021_dta_-555824136_index_2.json"
      }
    ]
  },
  {
    "title": "Doraemon Anime_L8",
    "link_thumb": "https://live.staticflickr.com/65535/51787205503_9aaa47e2fa_o.gif",
    "id_album": "405661398",
    "total": 16,
    "size_max_detail_page": 1,
    "list_detail": [
      {
        "index_page": 0,
        "link_page": "https://github.com/lmbstudiocontact/mb4_dt_alb_0/raw/main/14132021_dta_405661398_index_0.json"
      }
    ]
  },
  {
    "title": "Moana Cartoon_L2",
    "link_thumb": "https://live.staticflickr.com/65535/51787279463_0a59da48a6_o.gif",
    "id_album": "-2101867515",
    "total": 13,
    "size_max_detail_page": 1,
    "list_detail": [
      {
        "index_page": 0,
        "link_page": "https://github.com/lmbstudiocontact/mb4_dt_alb_0/raw/main/14132021_dta_-2101867515_index_0.json"
      }
    ]
  },
  {
    "title": "Other 1",
    "link_thumb": "https://live.staticflickr.com/65535/51787150893_5050a5e95b_o.gif",
    "id_album": "518493953",
    "total": 339,
    "size_max_detail_page": 7,
    "list_detail": [
      {
        "index_page": 0,
        "link_page": "https://github.com/lmbstudiocontact/mb4_dt_alb_0/raw/main/14132021_dta_518493953_index_0.json"
      },
      {
        "index_page": 1,
        "link_page": "https://github.com/lmbstudiocontact/mb4_dt_alb_0/raw/main/14132021_dta_518493953_index_1.json"
      },
      {
        "index_page": 2,
        "link_page": "https://github.com/lmbstudiocontact/mb4_dt_alb_0/raw/main/14132021_dta_518493953_index_2.json"
      },
      {
        "index_page": 3,
        "link_page": "https://github.com/lmbstudiocontact/mb4_dt_alb_0/raw/main/14132021_dta_518493953_index_3.json"
      },
      {
        "index_page": 4,
        "link_page": "https://github.com/lmbstudiocontact/mb4_dt_alb_0/raw/main/14132021_dta_518493953_index_4.json"
      },
      {
        "index_page": 5,
        "link_page": "https://github.com/lmbstudiocontact/mb4_dt_alb_0/raw/main/14132021_dta_518493953_index_5.json"
      },
      {
        "index_page": 6,
        "link_page": "https://github.com/lmbstudiocontact/mb4_dt_alb_0/raw/main/14132021_dta_518493953_index_6.json"
      }
    ]
  },
  {
    "title": "Ratatouille Cartoon_L5",
    "link_thumb": "https://live.staticflickr.com/65535/51787371568_605bc4d233_o.gif",
    "id_album": "1746345504",
    "total": 5,
    "size_max_detail_page": 1,
    "list_detail": [
      {
        "index_page": 0,
        "link_page": "https://github.com/lmbstudiocontact/mb4_dt_alb_0/raw/main/14132021_dta_1746345504_index_0.json"
      }
    ]
  },
  {
    "title": "Pokmon Anime_L6",
    "link_thumb": "https://live.staticflickr.com/65535/51787987855_7944f1e8bc_o.gif",
    "id_album": "-555824139",
    "total": 108,
    "size_max_detail_page": 3,
    "list_detail": [
      {
        "index_page": 0,
        "link_page": "https://github.com/lmbstudiocontact/mb4_dt_alb_0/raw/main/14132021_dta_-555824139_index_0.json"
      },
      {
        "index_page": 1,
        "link_page": "https://github.com/lmbstudiocontact/mb4_dt_alb_0/raw/main/14132021_dta_-555824139_index_1.json"
      },
      {
        "index_page": 2,
        "link_page": "https://github.com/lmbstudiocontact/mb4_dt_alb_0/raw/main/14132021_dta_-555824139_index_2.json"
      }
    ]
  },
  {
    "title": "Plants Vs Zombies_L6",
    "link_thumb": "https://live.staticflickr.com/65535/51787713749_a9020b44ea_o.gif",
    "id_album": "-1426777465",
    "total": 24,
    "size_max_detail_page": 1,
    "list_detail": [
      {
        "index_page": 0,
        "link_page": "https://github.com/lmbstudiocontact/mb4_dt_alb_0/raw/main/14132021_dta_-1426777465_index_0.json"
      }
    ]
  },
  {
    "title": "Cute Art_L9",
    "link_thumb": "https://live.staticflickr.com/65535/51787190043_4bded0f364_o.gif",
    "id_album": "-629963482",
    "total": 76,
    "size_max_detail_page": 2,
    "list_detail": [
      {
        "index_page": 0,
        "link_page": "https://github.com/lmbstudiocontact/mb4_dt_alb_0/raw/main/14132021_dta_-629963482_index_0.json"
      },
      {
        "index_page": 1,
        "link_page": "https://github.com/lmbstudiocontact/mb4_dt_alb_0/raw/main/14132021_dta_-629963482_index_1.json"
      }
    ]
  },
  {
    "title": "Moana Cartoon_L6",
    "link_thumb": "https://live.staticflickr.com/65535/51787023561_fe44c43408_o.gif",
    "id_album": "-2101867511",
    "total": 13,
    "size_max_detail_page": 1,
    "list_detail": [
      {
        "index_page": 0,
        "link_page": "https://github.com/lmbstudiocontact/mb4_dt_alb_0/raw/main/14132021_dta_-2101867511_index_0.json"
      }
    ]
  },
  {
    "title": "Spider Man Cartoon_L5",
    "link_thumb": "https://live.staticflickr.com/65535/51787764174_1ac99f55c8_o.gif",
    "id_album": "1735002395",
    "total": 16,
    "size_max_detail_page": 1,
    "list_detail": [
      {
        "index_page": 0,
        "link_page": "https://github.com/lmbstudiocontact/mb4_dt_alb_0/raw/main/14132021_dta_1735002395_index_0.json"
      }
    ]
  },
  {
    "title": "Detective Conan_L7",
    "link_thumb": "https://live.staticflickr.com/65535/51786941356_8390ede63a_o.gif",
    "id_album": "-1285383386",
    "total": 16,
    "size_max_detail_page": 1,
    "list_detail": [
      {
        "index_page": 0,
        "link_page": "https://github.com/lmbstudiocontact/mb4_dt_alb_0/raw/main/14132021_dta_-1285383386_index_0.json"
      }
    ]
  },
  {
    "title": "Onmyoji_L7",
    "link_thumb": "https://live.staticflickr.com/65535/51787942510_f550788606_o.gif",
    "id_album": "389318919",
    "total": 26,
    "size_max_detail_page": 1,
    "list_detail": [
      {
        "index_page": 0,
        "link_page": "https://github.com/lmbstudiocontact/mb4_dt_alb_0/raw/main/14132021_dta_389318919_index_0.json"
      }
    ]
  },
  {
    "title": "Naruto Anime_L8",
    "link_thumb": "https://live.staticflickr.com/65535/51787673649_bff6fcba35_o.gif",
    "id_album": "1894397990",
    "total": 37,
    "size_max_detail_page": 1,
    "list_detail": [
      {
        "index_page": 0,
        "link_page": "https://github.com/lmbstudiocontact/mb4_dt_alb_0/raw/main/14132021_dta_1894397990_index_0.json"
      }
    ]
  },
  {
    "title": "Lilo & Stitch Cartoon_L5",
    "link_thumb": "https://live.staticflickr.com/65535/51786203952_669d94a15d_o.gif",
    "id_album": "685543663",
    "total": 30,
    "size_max_detail_page": 1,
    "list_detail": [
      {
        "index_page": 0,
        "link_page": "https://github.com/lmbstudiocontact/mb4_dt_alb_0/raw/main/14132021_dta_685543663_index_0.json"
      }
    ]
  },
  {
    "title": "Kitty & My Melody_L5",
    "link_thumb": "https://live.staticflickr.com/65535/51787029276_b790a9e552_o.gif",
    "id_album": "-378480541",
    "total": 76,
    "size_max_detail_page": 2,
    "list_detail": [
      {
        "index_page": 0,
        "link_page": "https://github.com/lmbstudiocontact/mb4_dt_alb_0/raw/main/14132021_dta_-378480541_index_0.json"
      },
      {
        "index_page": 1,
        "link_page": "https://github.com/lmbstudiocontact/mb4_dt_alb_0/raw/main/14132021_dta_-378480541_index_1.json"
      }
    ]
  },
  {
    "title": "One Piece Anime_L4",
    "link_thumb": "https://live.staticflickr.com/65535/51787300333_c3af2e803a_o.gif",
    "id_album": "1351456607",
    "total": 135,
    "size_max_detail_page": 3,
    "list_detail": [
      {
        "index_page": 0,
        "link_page": "https://github.com/lmbstudiocontact/mb4_dt_alb_0/raw/main/14132021_dta_1351456607_index_0.json"
      },
      {
        "index_page": 1,
        "link_page": "https://github.com/lmbstudiocontact/mb4_dt_alb_0/raw/main/14132021_dta_1351456607_index_1.json"
      },
      {
        "index_page": 2,
        "link_page": "https://github.com/lmbstudiocontact/mb4_dt_alb_0/raw/main/14132021_dta_1351456607_index_2.json"
      }
    ]
  },
  {
    "title": "Fox Art_L10",
    "link_thumb": "https://live.staticflickr.com/65535/51787212788_ffe4e037f7_o.gif",
    "id_album": "1445399806",
    "total": 7,
    "size_max_detail_page": 1,
    "list_detail": [
      {
        "index_page": 0,
        "link_page": "https://github.com/lmbstudiocontact/mb4_dt_alb_0/raw/main/14132021_dta_1445399806_index_0.json"
      }
    ]
  },
  {
    "title": "Ghibli Anime_L4",
    "link_thumb": "https://live.staticflickr.com/65535/51786146882_5e7356b5c4_o.gif",
    "id_album": "-749595044",
    "total": 17,
    "size_max_detail_page": 1,
    "list_detail": [
      {
        "index_page": 0,
        "link_page": "https://github.com/lmbstudiocontact/mb4_dt_alb_0/raw/main/14132021_dta_-749595044_index_0.json"
      }
    ]
  },
  {
    "title": "Moana Cartoon_L10",
    "link_thumb": "https://live.staticflickr.com/65535/51787020876_9a49717808_o.gif",
    "id_album": "-733383508",
    "total": 13,
    "size_max_detail_page": 1,
    "list_detail": [
      {
        "index_page": 0,
        "link_page": "https://github.com/lmbstudiocontact/mb4_dt_alb_0/raw/main/14132021_dta_-733383508_index_0.json"
      }
    ]
  },
  {
    "title": "Smurf Houses Cartoon_L4",
    "link_thumb": "https://live.staticflickr.com/65535/51787385853_e4c423b290_o.gif",
    "id_album": "228264853",
    "total": 4,
    "size_max_detail_page": 1,
    "list_detail": [
      {
        "index_page": 0,
        "link_page": "https://github.com/lmbstudiocontact/mb4_dt_alb_0/raw/main/14132021_dta_228264853_index_0.json"
      }
    ]
  },
  {
    "title": "Boss Baby Cartoon_L7",
    "link_thumb": "https://live.staticflickr.com/65535/51787545169_a6b84a1e11_o.gif",
    "id_album": "158762707",
    "total": 16,
    "size_max_detail_page": 1,
    "list_detail": [
      {
        "index_page": 0,
        "link_page": "https://github.com/lmbstudiocontact/mb4_dt_alb_0/raw/main/14132021_dta_158762707_index_0.json"
      }
    ]
  },
  {
    "title": "Simpsons Cartoon_L9",
    "link_thumb": "https://live.staticflickr.com/65535/51787392668_71b1e70530_o.gif",
    "id_album": "1276946596",
    "total": 8,
    "size_max_detail_page": 1,
    "list_detail": [
      {
        "index_page": 0,
        "link_page": "https://github.com/lmbstudiocontact/mb4_dt_alb_0/raw/main/14132021_dta_1276946596_index_0.json"
      }
    ]
  },
  {
    "title": "Cute Art_L10",
    "link_thumb": "https://live.staticflickr.com/65535/51786085382_4b4c86afe4_o.gif",
    "id_album": "1945968338",
    "total": 75,
    "size_max_detail_page": 2,
    "list_detail": [
      {
        "index_page": 0,
        "link_page": "https://github.com/lmbstudiocontact/mb4_dt_alb_0/raw/main/14132021_dta_1945968338_index_0.json"
      },
      {
        "index_page": 1,
        "link_page": "https://github.com/lmbstudiocontact/mb4_dt_alb_0/raw/main/14132021_dta_1945968338_index_1.json"
      }
    ]
  },
  {
    "title": "Raccoons_L9",
    "link_thumb": "https://live.staticflickr.com/65535/51787372363_6f9e8d9d6e_o.gif",
    "id_album": "1998705272",
    "total": 20,
    "size_max_detail_page": 1,
    "list_detail": [
      {
        "index_page": 0,
        "link_page": "https://github.com/lmbstudiocontact/mb4_dt_alb_0/raw/main/14132021_dta_1998705272_index_0.json"
      }
    ]
  },
  {
    "title": "Panda Art_L10",
    "link_thumb": "https://live.staticflickr.com/65535/51787957770_a6aab3cc67_o.gif",
    "id_album": "1003935497",
    "total": 5,
    "size_max_detail_page": 1,
    "list_detail": [
      {
        "index_page": 0,
        "link_page": "https://github.com/lmbstudiocontact/mb4_dt_alb_0/raw/main/14132021_dta_1003935497_index_0.json"
      }
    ]
  },
  {
    "title": "Detective Conan_L5",
    "link_thumb": "https://live.staticflickr.com/65535/51787568534_95ae1c06a5_o.gif",
    "id_album": "-1285383388",
    "total": 16,
    "size_max_detail_page": 1,
    "list_detail": [
      {
        "index_page": 0,
        "link_page": "https://github.com/lmbstudiocontact/mb4_dt_alb_0/raw/main/14132021_dta_-1285383388_index_0.json"
      }
    ]
  },
  {
    "title": "Spider Man Cartoon_L4",
    "link_thumb": "https://live.staticflickr.com/65535/51786324462_74bf81b52b_o.gif",
    "id_album": "1735002394",
    "total": 16,
    "size_max_detail_page": 1,
    "list_detail": [
      {
        "index_page": 0,
        "link_page": "https://github.com/lmbstudiocontact/mb4_dt_alb_0/raw/main/14132021_dta_1735002394_index_0.json"
      }
    ]
  },
  {
    "title": "Animal Art_L3",
    "link_thumb": "https://live.staticflickr.com/65535/51787171103_f9015a302c_o.gif",
    "id_album": "97007463",
    "total": 7,
    "size_max_detail_page": 1,
    "list_detail": [
      {
        "index_page": 0,
        "link_page": "https://github.com/lmbstudiocontact/mb4_dt_alb_0/raw/main/14132021_dta_97007463_index_0.json"
      }
    ]
  },
  {
    "title": "Panda Art_L9",
    "link_thumb": "https://live.staticflickr.com/65535/51787335668_06ee0f0fd0_o.gif",
    "id_album": "586574351",
    "total": 5,
    "size_max_detail_page": 1,
    "list_detail": [
      {
        "index_page": 0,
        "link_page": "https://github.com/lmbstudiocontact/mb4_dt_alb_0/raw/main/14132021_dta_586574351_index_0.json"
      }
    ]
  }
]