[
  {
    "title": "Boss Baby Cartoon_L7",
    "link_thumb": "https://live.staticflickr.com/65535/51787545169_a6b84a1e11_o.gif",
    "id_album": "158762707",
    "total": 16,
    "size_max_detail_page": 1,
    "list_detail": [
      {
        "index_page": 0,
        "link_page": "https://github.com/lmbstudiocontact/mb4_dt_alb_0/raw/main/14132021_dta_158762707_index_0.json"
      }
    ]
  },
  {
    "title": "Butterfly_L4",
    "link_thumb": "https://live.staticflickr.com/65535/51786923646_dca5f6427b_o.gif",
    "id_album": "657564372",
    "total": 6,
    "size_max_detail_page": 1,
    "list_detail": [
      {
        "index_page": 0,
        "link_page": "https://github.com/lmbstudiocontact/mb4_dt_alb_0/raw/main/14132021_dta_657564372_index_0.json"
      }
    ]
  },
  {
    "title": "One Piece Anime_L8",
    "link_thumb": "https://live.staticflickr.com/65535/51787306798_e6477f7791_o.gif",
    "id_album": "1351456611",
    "total": 135,
    "size_max_detail_page": 3,
    "list_detail": [
      {
        "index_page": 0,
        "link_page": "https://github.com/lmbstudiocontact/mb4_dt_alb_0/raw/main/14132021_dta_1351456611_index_0.json"
      },
      {
        "index_page": 1,
        "link_page": "https://github.com/lmbstudiocontact/mb4_dt_alb_0/raw/main/14132021_dta_1351456611_index_1.json"
      },
      {
        "index_page": 2,
        "link_page": "https://github.com/lmbstudiocontact/mb4_dt_alb_0/raw/main/14132021_dta_1351456611_index_2.json"
      }
    ]
  },
  {
    "title": "Mickey Cartoon_L4",
    "link_thumb": "https://live.staticflickr.com/65535/51787645544_6e3eb8c47b_o.gif",
    "id_album": "1680949825",
    "total": 22,
    "size_max_detail_page": 1,
    "list_detail": [
      {
        "index_page": 0,
        "link_page": "https://github.com/lmbstudiocontact/mb4_dt_alb_0/raw/main/14132021_dta_1680949825_index_0.json"
      }
    ]
  },
  {
    "title": "Onmyoji_L9",
    "link_thumb": "https://live.staticflickr.com/65535/51787090921_6e07356969_o.gif",
    "id_album": "389318921",
    "total": 26,
    "size_max_detail_page": 1,
    "list_detail": [
      {
        "index_page": 0,
        "link_page": "https://github.com/lmbstudiocontact/mb4_dt_alb_0/raw/main/14132021_dta_389318921_index_0.json"
      }
    ]
  },
  {
    "title": "Language Turkish_Animation",
    "link_thumb": "https://live.staticflickr.com/65535/51786075397_b7bb3671fe_o.gif",
    "id_album": "280554465",
    "total": 6,
    "size_max_detail_page": 1,
    "list_detail": [
      {
        "index_page": 0,
        "link_page": "https://github.com/lmbstudiocontact/mb4_dt_alb_0/raw/main/14132021_dta_280554465_index_0.json"
      }
    ]
  },
  {
    "title": "Madagascar Cartoon_L10",
    "link_thumb": "https://live.staticflickr.com/65535/51786195957_44a9f50517_o.gif",
    "id_album": "1973695398",
    "total": 9,
    "size_max_detail_page": 1,
    "list_detail": [
      {
        "index_page": 0,
        "link_page": "https://github.com/lmbstudiocontact/mb4_dt_alb_0/raw/main/14132021_dta_1973695398_index_0.json"
      }
    ]
  },
  {
    "title": "The Lion King Cartoon",
    "link_thumb": "https://live.staticflickr.com/65535/51787773640_a9650e597d_o.gif",
    "id_album": "-1345256646",
    "total": 6,
    "size_max_detail_page": 1,
    "list_detail": [
      {
        "index_page": 0,
        "link_page": "https://github.com/lmbstudiocontact/mb4_dt_alb_0/raw/main/14132021_dta_-1345256646_index_0.json"
      }
    ]
  },
  {
    "title": "Kitty & My Melody_L1",
    "link_thumb": "https://live.staticflickr.com/65535/51786203482_195a5c4f42_o.gif",
    "id_album": "-378480545",
    "total": 76,
    "size_max_detail_page": 2,
    "list_detail": [
      {
        "index_page": 0,
        "link_page": "https://github.com/lmbstudiocontact/mb4_dt_alb_0/raw/main/14132021_dta_-378480545_index_0.json"
      },
      {
        "index_page": 1,
        "link_page": "https://github.com/lmbstudiocontact/mb4_dt_alb_0/raw/main/14132021_dta_-378480545_index_1.json"
      }
    ]
  },
  {
    "title": "Music_L5",
    "link_thumb": "https://live.staticflickr.com/65535/51787024611_19071fb2d2_o.gif",
    "id_album": "908522979",
    "total": 24,
    "size_max_detail_page": 1,
    "list_detail": [
      {
        "index_page": 0,
        "link_page": "https://github.com/lmbstudiocontact/mb4_dt_alb_0/raw/main/14132021_dta_908522979_index_0.json"
      }
    ]
  }
]