[
  {
    "title": "Naruto Anime_L4",
    "link_thumb": "https://live.staticflickr.com/65535/51787298578_6acda6b96c_o.gif",
    "id_album": "1894397986",
    "total": 37,
    "size_max_detail_page": 1,
    "list_detail": [
      {
        "index_page": 0,
        "link_page": "https://github.com/lmbstudiocontact/mb4_dt_alb_0/raw/main/14132021_dta_1894397986_index_0.json"
      }
    ]
  },
  {
    "title": "Frozen Cartoon_L10",
    "link_thumb": "https://live.staticflickr.com/65535/51786137607_cf63f7ca57_o.gif",
    "id_album": "788725146",
    "total": 11,
    "size_max_detail_page": 1,
    "list_detail": [
      {
        "index_page": 0,
        "link_page": "https://github.com/lmbstudiocontact/mb4_dt_alb_0/raw/main/14132021_dta_788725146_index_0.json"
      }
    ]
  },
  {
    "title": "Onmyoji_L2",
    "link_thumb": "https://live.staticflickr.com/65535/51787697219_f27857cf46_o.gif",
    "id_album": "389318914",
    "total": 26,
    "size_max_detail_page": 1,
    "list_detail": [
      {
        "index_page": 0,
        "link_page": "https://github.com/lmbstudiocontact/mb4_dt_alb_0/raw/main/14132021_dta_389318914_index_0.json"
      }
    ]
  },
  {
    "title": "Plants Vs Zombies_L10",
    "link_thumb": "https://live.staticflickr.com/65535/51787070016_499775d41d_o.gif",
    "id_album": "-1280428562",
    "total": 24,
    "size_max_detail_page": 1,
    "list_detail": [
      {
        "index_page": 0,
        "link_page": "https://github.com/lmbstudiocontact/mb4_dt_alb_0/raw/main/14132021_dta_-1280428562_index_0.json"
      }
    ]
  },
  {
    "title": "Doraemon Anime_L10",
    "link_thumb": "https://live.staticflickr.com/65535/51787185523_79ec7ef162_o.gif",
    "id_album": "-309398719",
    "total": 16,
    "size_max_detail_page": 1,
    "list_detail": [
      {
        "index_page": 0,
        "link_page": "https://github.com/lmbstudiocontact/mb4_dt_alb_0/raw/main/14132021_dta_-309398719_index_0.json"
      }
    ]
  },
  {
    "title": "Joker Harley Quinn_L4",
    "link_thumb": "https://live.staticflickr.com/65535/51786172482_4c83f55268_o.gif",
    "id_album": "-2022175634",
    "total": 24,
    "size_max_detail_page": 1,
    "list_detail": [
      {
        "index_page": 0,
        "link_page": "https://github.com/lmbstudiocontact/mb4_dt_alb_0/raw/main/14132021_dta_-2022175634_index_0.json"
      }
    ]
  },
  {
    "title": "Animals",
    "link_thumb": "https://live.staticflickr.com/65535/51786080827_95f4473e73_o.gif",
    "id_album": "807717335",
    "total": 114,
    "size_max_detail_page": 3,
    "list_detail": [
      {
        "index_page": 0,
        "link_page": "https://github.com/lmbstudiocontact/mb4_dt_alb_0/raw/main/14132021_dta_807717335_index_0.json"
      },
      {
        "index_page": 1,
        "link_page": "https://github.com/lmbstudiocontact/mb4_dt_alb_0/raw/main/14132021_dta_807717335_index_1.json"
      },
      {
        "index_page": 2,
        "link_page": "https://github.com/lmbstudiocontact/mb4_dt_alb_0/raw/main/14132021_dta_807717335_index_2.json"
      }
    ]
  },
  {
    "title": "Madagascar Cartoon_L10",
    "link_thumb": "https://live.staticflickr.com/65535/51786195957_44a9f50517_o.gif",
    "id_album": "1973695398",
    "total": 9,
    "size_max_detail_page": 1,
    "list_detail": [
      {
        "index_page": 0,
        "link_page": "https://github.com/lmbstudiocontact/mb4_dt_alb_0/raw/main/14132021_dta_1973695398_index_0.json"
      }
    ]
  },
  {
    "title": "Kung Fu Panda_L3",
    "link_thumb": "https://live.staticflickr.com/65535/51787878605_c8a1d2b7cd_o.gif",
    "id_album": "1222783552",
    "total": 2,
    "size_max_detail_page": 1,
    "list_detail": [
      {
        "index_page": 0,
        "link_page": "https://github.com/lmbstudiocontact/mb4_dt_alb_0/raw/main/14132021_dta_1222783552_index_0.json"
      }
    ]
  },
  {
    "title": "Buddhist Terms_L6",
    "link_thumb": "https://live.staticflickr.com/65535/51787534054_2087065639_o.gif",
    "id_album": "518853933",
    "total": 13,
    "size_max_detail_page": 1,
    "list_detail": [
      {
        "index_page": 0,
        "link_page": "https://github.com/lmbstudiocontact/mb4_dt_alb_0/raw/main/14132021_dta_518853933_index_0.json"
      }
    ]
  }
]